pydantic_db_backend/__init__.py
pydantic_db_backend/backend.py
pydantic_db_backend/backends/__init__.py
pydantic_db_backend/backends/couchdb.py
pydantic_db_backend/backends/mongodb.py
pydantic_db_backend/contexts/__init__.py
pydantic_db_backend/contexts/custom_aggregation.py
pydantic_db_backend/contexts/pagination_parameter.py
pydantic_db_backend/fastapi.py
pydantic_db_backend/pagination.py
pydantic_db_backend/utils.py
pydantic_db_backend-3.4.0.dist-info/METADATA
pydantic_db_backend-3.4.0.dist-info/WHEEL
pydantic_db_backend-3.4.0.dist-info/RECORD
