Metadata-Version: 2.1
Name: pydantic-db-backend
Version: 3.4.0
Summary: 
Author: Marco Bartel
Author-email: bsimpson888@gmail.com
Requires-Python: >=3.11,<4.0
Classifier: Programming Language :: Python :: 3
Classifier: Programming Language :: Python :: 3.11
Provides-Extra: couchdb
Provides-Extra: mongodb
Requires-Dist: couchdb (>=1.2,<2.0) ; extra == "couchdb"
Requires-Dist: pydantic (>=2.4.2,<3.0.0)
Requires-Dist: pydantic-db-backend-common (>=2.3.1,<3.0.0)
Requires-Dist: pydantic-settings (>=2.0.3,<3.0.0)
Requires-Dist: pydash
Requires-Dist: pymongo (>=3.13.0,<4.0.0) ; extra == "mongodb"
Requires-Dist: python-dotenv (>=1.0.0,<2.0.0)
Requires-Dist: webexception (>=1.0.4,<2.0.0)
